tensorpotential/__init__.py
tensorpotential/constants.py
tensorpotential/export.py
tensorpotential/loss.py
tensorpotential/metrics.py
tensorpotential/poly.py
tensorpotential/tensorpot.py
tensorpotential/tpmodel.py
tensorpotential/utils.py
tensorpotential/calculator/__init__.py
tensorpotential/calculator/asecalculator.py
tensorpotential/calculator/foundation_models.py
tensorpotential/cli/__init__.py
tensorpotential/cli/data.py
tensorpotential/cli/gracemaker.py
tensorpotential/cli/prepare.py
tensorpotential/cli/train.py
tensorpotential/cli/train_callbacks.py
tensorpotential/compat/__init__.py
tensorpotential/compat/pace/__init__.py
tensorpotential/compat/pace/_version.py
tensorpotential/compat/pace/constants.py
tensorpotential/compat/pace/fit.py
tensorpotential/compat/pace/fitmetrics.py
tensorpotential/compat/pace/tensorpot.py
tensorpotential/compat/pace/functions/__init__.py
tensorpotential/compat/pace/functions/radial_functions.py
tensorpotential/compat/pace/functions/spherical_harmonics.py
tensorpotential/compat/pace/potentials/__init__.py
tensorpotential/compat/pace/potentials/ace.py
tensorpotential/compat/pace/utils/__init__.py
tensorpotential/compat/pace/utils/neighborlist.py
tensorpotential/compat/pace/utils/symbols.py
tensorpotential/compat/pace/utils/tensorcalc.py
tensorpotential/compat/pace/utils/utilities.py
tensorpotential/data/__init__.py
tensorpotential/data/databuilder.py
tensorpotential/data/dataset_plotter.py
tensorpotential/data/process_df.py
tensorpotential/data/symbols.py
tensorpotential/data/tpatoms.py
tensorpotential/data/weighting.py
tensorpotential/functions/__init__.py
tensorpotential/functions/couplings.py
tensorpotential/functions/lora.py
tensorpotential/functions/nn.py
tensorpotential/functions/radial.py
tensorpotential/functions/spherical_harmonics.py
tensorpotential/instructions/__init__.py
tensorpotential/instructions/base.py
tensorpotential/instructions/compute.py
tensorpotential/instructions/output.py
tensorpotential-0.5.6.dist-info/licenses/LICENSE.md
tensorpotential-0.5.6.dist-info/METADATA
tensorpotential-0.5.6.dist-info/WHEEL
tensorpotential-0.5.6.dist-info/entry_points.txt
tensorpotential-0.5.6.dist-info/top_level.txt
tensorpotential-0.5.6.dist-info/RECORD
