Metadata-Version: 2.4
Name: tensorpotential
Version: 0.5.6
Summary: Graph Atomic Cluster Expansion (GRACE)
Author-email: Anton Bochkarev <anton.bochkarev@rub.de>, Yury Lysogorskiy <yury.lysogorskiy@rub.de>
License: Academic Software License (ASL)
Project-URL: Homepage, https://github.com/ICAMS/grace-tensorpotential
Classifier: License :: OSI Approved :: Academic Free License (AFL)
Classifier: Programming Language :: Python :: 3
Classifier: Programming Language :: Python :: 3.9
Classifier: Programming Language :: Python :: 3.10
Classifier: Programming Language :: Python :: 3.11
Classifier: Programming Language :: Python :: 3.12
Requires-Python: <3.13,>=3.9
License-File: LICENSE.md
Requires-Dist: tensorflow<2.20; sys_platform == "win32" or sys_platform == "darwin"
Requires-Dist: tensorflow[and-cuda]<2.20; sys_platform == "linux"
Requires-Dist: tf_keras
Requires-Dist: scipy
Requires-Dist: matscipy
Requires-Dist: numpy<3.0.0
Requires-Dist: sympy
Requires-Dist: pandas<3.0.0
Requires-Dist: ase
Requires-Dist: pyyaml>=6.0.2
Requires-Dist: tqdm
Dynamic: license-file
